xtal/__init__.py
xtal-0.9.2.dist-info/LICENSE
xtal-0.9.2.dist-info/METADATA
xtal-0.9.2.dist-info/WHEEL
xtal-0.9.2.dist-info/top_level.txt
xtal-0.9.2.dist-info/RECORD
