Metadata-Version: 2.1
Name: xtal
Version: 0.9.2
Summary: Tools to manipulate atomic trajectories
Home-page: https://github.com/USCCACS/xtal
Author: Aravind Krishnamoorthy
Author-email: arvk@users.noreply.github.com
License: MIT
Platform: UNKNOWN
Requires-Dist: numpy (>=1.15.0)
